avatar2/__init__.py
avatar2/avatar2.py
avatar2/memory_range.py
avatar2/message.py
avatar2/watchmen.py
avatar2/archs/__init__.py
avatar2/archs/architecture.py
avatar2/archs/arm.py
avatar2/archs/mips.py
avatar2/archs/x86.py
avatar2/installer/__init__.py
avatar2/installer/__main__.py
avatar2/installer/avatar2_installer.py
avatar2/installer/config.py
avatar2/peripherals/__init__.py
avatar2/peripherals/avatar_peripheral.py
avatar2/peripherals/max32_usart.py
avatar2/peripherals/nucleo_usart.py
avatar2/plugins/__init__.py
avatar2/plugins/assembler.py
avatar2/plugins/disassembler.py
avatar2/plugins/gdb_core_dumper.py
avatar2/plugins/gdb_memory_map_loader.py
avatar2/plugins/gdbserver.py
avatar2/plugins/instruction_forwarder.py
avatar2/plugins/orchestrator.py
avatar2/plugins/arm/__init__.py
avatar2/plugins/arm/armv7m_interrupts.py
avatar2/plugins/arm/coresight_finder.py
avatar2/plugins/arm/svd_mapper.py
avatar2/plugins/arm/unicorn_caller.py
avatar2/plugins/gdb/arm-target.xml
avatar2/plugins/gdb/x86_64-target.xml
avatar2/protocols/__init__.py
avatar2/protocols/armv7m_interrupt.py
avatar2/protocols/coresight.py
avatar2/protocols/gdb.py
avatar2/protocols/inception.py
avatar2/protocols/jlink.py
avatar2/protocols/openocd.py
avatar2/protocols/qmp.py
avatar2/protocols/remote_memory.py
avatar2/protocols/unicorn_protocol.py
avatar2/targets/__init__.py
avatar2/targets/dummy_target.py
avatar2/targets/gdb_target.py
avatar2/targets/inception_target.py
avatar2/targets/jlink_target.py
avatar2/targets/openocd_target.py
avatar2/targets/panda_target.py
avatar2/targets/pypanda_target.py
avatar2/targets/qemu_target.py
avatar2/targets/target.py
avatar2/targets/unicorn_target.py
avatar2-1.4.7.dist-info/LICENSE
avatar2-1.4.7.dist-info/METADATA
avatar2-1.4.7.dist-info/WHEEL
avatar2-1.4.7.dist-info/top_level.txt
avatar2-1.4.7.dist-info/RECORD
