Metadata-Version: 1.2
Name: avatar2
Version: 1.4.7
Summary: A Dynamic Multi-Target Orchestration Framework
Home-page: https://github.com/avatartwo/avatar2
Maintainer: Marius Muench
Maintainer-email: marius.muench@eurecom.fr
License: UNKNOWN
Platform: UNKNOWN
